effectus/__init__.py
effectus/cli.py
effectus/core.py
effectus/data.py
effectus/exceptions.py
effectus/helpers.py
effectus/pareto.py
effectus/csv/bells.csv
effectus/csv/boxoffice.csv
effectus/csv/cheese.csv
effectus/csv/countries_area.csv
effectus/csv/countries_population.csv
effectus/csv/gdp.csv
effectus/csv/german_highways.csv
effectus/csv/german_motorways.csv
effectus/csv/hopei_rain.csv
effectus/csv/hopei_sun.csv
effectus/csv/missing_teeth.csv
effectus/csv/readCSV.hs~
effectus/csv/sp500.csv
effectus/csv/wkzs.csv
effectus/csv/women_intercourse.csv
effectus-1.0.0.dev4.dist-info/DESCRIPTION.rst
effectus-1.0.0.dev4.dist-info/METADATA
effectus-1.0.0.dev4.dist-info/RECORD
effectus-1.0.0.dev4.dist-info/WHEEL
effectus-1.0.0.dev4.dist-info/entry_points.txt
effectus-1.0.0.dev4.dist-info/metadata.json
effectus-1.0.0.dev4.dist-info/top_level.txt
