Metadata-Version: 2.0
Name: effectus
Version: 1.0.0.dev4
Summary: effectus tells you which minority of causes provokes which majority of effects.
Home-page: http://bitbucket.com/hyllos/effectus-python
Author: Benjamin Weber
Author-email: mail@bwe.im
License: MIT license
Keywords: pareto cause-effect power-law entropy
Platform: UNKNOWN
Classifier: Development Status :: 4 - Beta
Classifier: License :: OSI Approved :: MIT License
Classifier: Programming Language :: Python :: 3
Classifier: Programming Language :: Python :: 3.5
Classifier: Programming Language :: Python :: 3.6
Requires-Dist: click
Requires-Dist: quicktions
Requires-Dist: xlwings
